<?xml version='1.0' encoding='UTF-8'?>
<song xmlns="http://openlyrics.info/namespace/2009/song" version="0.8" createdIn="OpenLP 3.0.2" modifiedIn="OpenLP 3.0.2" modifiedDate="2023-12-17T05:57:43">
  <properties>
    <titles>
      <title>He Keeps Me Singing</title>
    </titles>
    <copyright>Public Domain</copyright>
    <authors>
      <author>Luther B. Bridgers</author>
    </authors>
  </properties>
  <lyrics>
    <verse name="c1a">
      <lines>Jesus, Jesus, Jesus,<br/>Sweetest name I know,</lines>
    </verse>
    <verse name="c1b">
      <lines>Fills my ev'ry longing,<br/>Keeps me singing as I go.</lines>
    </verse>
    <verse name="v1a">
      <lines>There's within my heart<br/>a melody.<br/><br/>Jesus whispers<br/>sweet and low:</lines>
    </verse>
    <verse name="v1b">
      <lines>"Fear not, I am with thee;<br/>peace, be still,"<br/><br/>In all of life's<br/>ebb and flow.</lines>
    </verse>
    <verse name="v2a">
      <lines>All my life was wrecked<br/>by sin and strife;<br/><br/>Discord filled my heart<br/>with pain.</lines>
    </verse>
    <verse name="v2b">
      <lines>Jesus swept across<br/>the broken strings,<br/><br/>Stirred the slumb'ring<br/>chords again.</lines>
    </verse>
    <verse name="v3a">
      <lines>Feasting on the riches<br/>of His grace,<br/><br/>Resting 'neath<br/>His shelt'ring wing,</lines>
    </verse>
    <verse name="v3b">
      <lines>Always looking on<br/>His smiling face,<br/><br/>That is why<br/>I shout and sing.</lines>
    </verse>
    <verse name="v4a">
      <lines>Tho' sometimes He leads<br/>thro' waters deep,<br/><br/>Trials fall across<br/>my way,</lines>
    </verse>
    <verse name="v4b">
      <lines>Tho' sometimes the path<br/>seems rough and steep,<br/><br/>See His footprints<br/>all the way.</lines>
    </verse>
    <verse name="v5a">
      <lines>Soon He's coming back<br/>to welcome me<br/><br/>Far beyond<br/>the starry sky.</lines>
    </verse>
    <verse name="v5b">
      <lines>I shall wing my flight<br/>to worlds unknown;<br/><br/>I shall reign with Him<br/>on high.</lines>
    </verse>
  </lyrics>
</song>
