<?xml version='1.0' encoding='UTF-8'?>
<song xmlns="http://openlyrics.info/namespace/2009/song" version="0.8" createdIn="OpenLP 3.0.2" modifiedIn="OpenLP 3.0.2" modifiedDate="2024-01-07T03:47:45">
  <properties>
    <titles>
      <title>Since Jesus Came Into My Heart</title>
    </titles>
    <copyright>Public Domain</copyright>
    <authors>
      <author>Charles H. Gabriel Rufus H. McDaniel</author>
    </authors>
  </properties>
  <lyrics>
    <verse name="c1a">
      <lines>Since Jesus came into my heart,<br/><br/>Since Jesus came into my heart,</lines>
    </verse>
    <verse name="c1b">
      <lines>Floods of joy o'er my soul<br/>like the sea billows roll,<br/><br/>Since Jesus came into my heart.</lines>
    </verse>
    <verse name="v1a">
      <lines>What a wonderful change<br/>in my life has been wrought<br/><br/>Since Jesus came into my heart!</lines>
    </verse>
    <verse name="v1b">
      <lines>I have light in my soul,<br/>for which long I have sought,<br/><br/>Since Jesus came into my heart.</lines>
    </verse>
    <verse name="v2a">
      <lines>I have ceased from my<br/>wandering and going astray<br/><br/>Since Jesus came into my heart;</lines>
    </verse>
    <verse name="v2b">
      <lines>And my sins which were many<br/>are all washed away,<br/><br/>Since Jesus came into my heart.</lines>
    </verse>
    <verse name="v3a">
      <lines>There's a light in the<br/>valley of death now for me,<br/><br/>Since Jesus came into my heart;</lines>
    </verse>
    <verse name="v3b">
      <lines>And the gates of the city<br/>beyond I can see,<br/><br/>Since Jesus came into my heart.</lines>
    </verse>
    <verse name="v4a">
      <lines>I shall go there to dwell<br/>in that city I know,<br/><br/>Since Jesus came into my heart;</lines>
    </verse>
    <verse name="v4b">
      <lines>And I'm happy, so happy,<br/>as onward I go,<br/><br/>Since Jesus came into my heart.</lines>
    </verse>
    <verse name="v5a">
      <lines>I'm possessed of a hope<br/>that is steadfast and sure,<br/><br/>Since Jesus came into my heart;</lines>
    </verse>
    <verse name="v5b">
      <lines>And no dark clouds of doubt<br/>now my pathway obscure,<br/><br/>Since Jesus came into my heart.</lines>
    </verse>
  </lyrics>
</song>
